{
  "response": [
    {
      "maintainer": "Rocky7842",
      "oem": "Xiaomi",
      "device": "12X",
      "filename": "crDroidAndroid-15.0-20250524-psyche-v11.5.zip",
      "download": "https://github.com/Rocky7842/OTA_provider/releases/download/psyche-crDroid-11.5-20250524/crDroidAndroid-15.0-20250524-psyche-v11.5.zip",
      "timestamp": "1748087831",
      "md5": "05606a22c5c82ceef2a903a55cc38bd3",
      "sha256": "986ddc6e11578e0a12bd5ae9fa0a9c994186dd87183da9ba5f20dbb69c43e57c",
      "size": "1763320516",
      "version": "11.5",
      "buildtype": "Monthly",
      "forum": "https://xdaforums.com/t/4715823/",
      "gapps": "https://github.com/MindTheGapps/15.0.0-arm64/releases",
      "firmware": "",
      "modem": "",
      "bootloader": "",
      "recovery": "https://github.com/Rocky7842/OTA_provider/releases/download/psyche-crDroid-11.5-20250524/recovery.img",
      "paypal": "https://www.paypal.com/paypalme/EricRocky7842",
      "telegram": "",
      "dt": "https://github.com/Rocky7842/android_device_xiaomi_psyche",
      "common-dt": "https://github.com/Rocky7842/android_device_xiaomi_sm8250-common",
      "kernel": "https://github.com/Rocky7842/android_kernel_xiaomi_sm8250"
    }
  ]
}
