{
  "response": [
    {
      "maintainer": "Rocky7842",
      "oem": "Xiaomi",
      "device": "Mi 8 SE",
      "filename": "crDroidAndroid-14.0-20240515-xmsirius-v10.5.zip",
      "download": "https://sourceforge.net/projects/crdroid-xiaomi-8-se/files/crdroid-10/crDroidAndroid-14.0-20240515-xmsirius-v10.5.zip/download",
      "timestamp": "1715780996",
      "md5": "dfa0229bd0ba120e6a9104319048b9a1",
      "sha256": "94510c6ff138c4a443b17a6d7356f8b88aa37e9ec7fdf20de258696ba4006e78",
      "size": "1253502759",
      "version": "10.5",
      "buildtype": "Monthly",
      "forum": "https://xdaforums.com/t/4639873/",
      "gapps": "https://github.com/MindTheGapps/14.0.0-arm64/releases",
      "firmware": "",
      "modem": "",
      "bootloader": "",
      "recovery": "https://sourceforge.net/projects/crdroid-xiaomi-8-se/files/crdroid-10/recovery.img/download",
      "paypal": "https://www.paypal.com/paypalme/EricRocky7842",
      "telegram": "",
      "dt": "https://github.com/Rocky7842/android_device_xiaomi_xmsirius",
      "common-dt": "https://github.com/Rocky7842/android_device_xiaomi_sdm710-common",
      "kernel": "https://github.com/Rocky7842/android_kernel_xiaomi_sdm710"
    }
  ]
}
